weather_model_graphs-0.3.0.dist-info/METADATA
weather_model_graphs-0.3.0.dist-info/WHEEL
weather_model_graphs-0.3.0.dist-info/entry_points.txt
weather_model_graphs/__init__.py
weather_model_graphs/create/__init__.py
weather_model_graphs/create/archetype.py
weather_model_graphs/create/base.py
weather_model_graphs/create/grid/__init__.py
weather_model_graphs/create/grid/grid.py
weather_model_graphs/create/mesh/__init__.py
weather_model_graphs/create/mesh/kinds/__init__.py
weather_model_graphs/create/mesh/kinds/flat.py
weather_model_graphs/create/mesh/kinds/hierarchical.py
weather_model_graphs/create/mesh/mesh.py
weather_model_graphs/networkx_utils.py
weather_model_graphs/save.py
weather_model_graphs/visualise/__init__.py
weather_model_graphs/visualise/plot_2d.py
weather_model_graphs-0.3.0.dist-info/RECORD
