Metadata-Version: 2.1
Name: weather-model-graphs
Version: 0.3.0
Summary: Tools for creating and visualising data-driven weather model graphs
Author-Email: Leif Denby <lcd@dmi.dk>
License: MIT
Requires-Python: >=3.10
Requires-Dist: numpy>=1.26.4
Requires-Dist: loguru>=0.7.2
Requires-Dist: networkx>=3.3
Requires-Dist: scipy>=1.13.0
Requires-Dist: pyproj>=3.7.0
Provides-Extra: pytorch
Requires-Dist: torch>=2.3.0; extra == "pytorch"
Requires-Dist: torch-geometric>=2.5.3; extra == "pytorch"
Provides-Extra: visualisation
Requires-Dist: matplotlib>=3.8.4; extra == "visualisation"
Requires-Dist: ipykernel>=6.29.4; extra == "visualisation"
Requires-Dist: cartopy>=0.24.1; extra == "visualisation"
Provides-Extra: docs
Requires-Dist: jupyter-book>=1.0.0; extra == "docs"
Requires-Dist: sphinxcontrib-mermaid>=0.9.2; extra == "docs"
